number_convert/__init__.py
number_convert-1.0.1.dist-info/LICENSE
number_convert-1.0.1.dist-info/METADATA
number_convert-1.0.1.dist-info/WHEEL
number_convert-1.0.1.dist-info/top_level.txt
number_convert-1.0.1.dist-info/RECORD
